{"frames": [

{
	"filename": "blue",
	"frame": {"x":0,"y":0,"w":198,"h":198},
	"rotated": false,
	"trimmed": false,
	"spriteSourceSize": {"x":0,"y":0,"w":198,"h":198},
	"sourceSize": {"w":198,"h":198},
	"pivot": {"x":0.5,"y":0.5}
},
{
	"filename": "goal",
	"frame": {"x":198,"y":0,"w":198,"h":198},
	"rotated": false,
	"trimmed": false,
	"spriteSourceSize": {"x":0,"y":0,"w":198,"h":198},
	"sourceSize": {"w":198,"h":198},
	"pivot": {"x":0.5,"y":0.5}
},
{
	"filename": "green",
	"frame": {"x":0,"y":198,"w":198,"h":198},
	"rotated": false,
	"trimmed": false,
	"spriteSourceSize": {"x":0,"y":0,"w":198,"h":198},
	"sourceSize": {"w":198,"h":198},
	"pivot": {"x":0.5,"y":0.5}
},
{
	"filename": "player_1",
	"frame": {"x":396,"y":0,"w":107,"h":198},
	"rotated": false,
	"trimmed": true,
	"spriteSourceSize": {"x":44,"y":0,"w":107,"h":198},
	"sourceSize": {"w":198,"h":198},
	"pivot": {"x":0.5,"y":0.5}
},
{
	"filename": "player_2",
	"frame": {"x":0,"y":396,"w":107,"h":194},
	"rotated": false,
	"trimmed": true,
	"spriteSourceSize": {"x":44,"y":0,"w":107,"h":194},
	"sourceSize": {"w":198,"h":198},
	"pivot": {"x":0.5,"y":0.5}
},
{
	"filename": "player_3",
	"frame": {"x":0,"y":784,"w":107,"h":192},
	"rotated": false,
	"trimmed": true,
	"spriteSourceSize": {"x":44,"y":0,"w":107,"h":192},
	"sourceSize": {"w":198,"h":198},
	"pivot": {"x":0.5,"y":0.5}
},
{
	"filename": "player_4",
	"frame": {"x":0,"y":590,"w":106,"h":194},
	"rotated": false,
	"trimmed": true,
	"spriteSourceSize": {"x":45,"y":0,"w":106,"h":194},
	"sourceSize": {"w":198,"h":198},
	"pivot": {"x":0.5,"y":0.5}
},
{
	"filename": "player_5",
	"frame": {"x":396,"y":198,"w":107,"h":198},
	"rotated": false,
	"trimmed": true,
	"spriteSourceSize": {"x":44,"y":0,"w":107,"h":198},
	"sourceSize": {"w":198,"h":198},
	"pivot": {"x":0.5,"y":0.5}
},
{
	"filename": "red",
	"frame": {"x":198,"y":198,"w":198,"h":198},
	"rotated": false,
	"trimmed": false,
	"spriteSourceSize": {"x":0,"y":0,"w":198,"h":198},
	"sourceSize": {"w":198,"h":198},
	"pivot": {"x":0.5,"y":0.5}
}],
"meta": {
	"app": "http://www.codeandweb.com/texturepacker",
	"version": "1.0",
	"image": "main0.png",
	"format": "RGBA8888",
	"size": {"w":512,"h":1024},
	"scale": "1",
	"smartupdate": "$TexturePacker:SmartUpdate:4b0b8771d15b91f928135fd41ab47e56:8d6e7b1eed1043199662d179efb6d226:4eca5c461cff569e73cb53b7a0addea8$"
}
}
